setup.py
pkgboot/__init__.py
pkgboot/main.py
pkgboot/package.py
pkgboot.egg-info/PKG-INFO
pkgboot.egg-info/SOURCES.txt
pkgboot.egg-info/dependency_links.txt
pkgboot.egg-info/entry_points.txt
pkgboot.egg-info/pbr.json
pkgboot.egg-info/requires.txt
pkgboot.egg-info/top_level.txt