Metadata-Version: 1.0
Name: pkgboot
Version: 0.0.2
Summary: C++ workspace setup with SCons
Home-page: http://github.com/mfichman/pkgboot
Author: Matt Fichman
Author-email: matt.fichman@gmail.com
License: MIT
Keywords: installer,windows,workspace
Platform: UNKNOWN
